[
  {
    "id": "637f9036-a92d-4ed2-bb41-139da36ff508",
    "data": [
      {
        "text": "What are you?",
        "userDefined": false
      }
    ],
    "isTemplate": false,
    "count": 0,
    "updated": 1518261042
  },
  {
    "id": "76e6d789-26d2-46d9-a4dc-716e50029d75",
    "data": [
      {
        "text": "Tell me about the Wirral Wheelers",
        "userDefined": false
      }
    ],
    "isTemplate": false,
    "count": 0,
    "updated": 1518261042
  },
  {
    "id": "c2b96a69-5f6d-4b16-9cbf-5b3e780f0ff0",
    "data": [
      {
        "text": "Who are you",
        "userDefined": false
      }
    ],
    "isTemplate": false,
    "count": 0,
    "updated": 1518261042
  },
  {
    "id": "ace2bb14-3a1e-49dd-8ed2-c30323a70b43",
    "data": [
      {
        "text": "What is Wirral Wheelers",
        "userDefined": false
      }
    ],
    "isTemplate": false,
    "count": 0,
    "updated": 1518261042
  },
  {
    "id": "205e0b1a-d1ea-41c5-93ec-413e8eb15b11",
    "data": [
      {
        "text": "Tell me about Wirral Wheelers",
        "userDefined": false
      }
    ],
    "isTemplate": false,
    "count": 0,
    "updated": 1518261042
  }
]